shapely-stubs/METADATA.toml
shapely-stubs/__init__.pyi
shapely-stubs/_coverage.pyi
shapely-stubs/_enum.pyi
shapely-stubs/_geometry.pyi
shapely-stubs/_ragged_array.pyi
shapely-stubs/_typing.pyi
shapely-stubs/_version.pyi
shapely-stubs/affinity.pyi
shapely-stubs/constructive.pyi
shapely-stubs/coordinates.pyi
shapely-stubs/coords.pyi
shapely-stubs/creation.pyi
shapely-stubs/decorators.pyi
shapely-stubs/errors.pyi
shapely-stubs/geos.pyi
shapely-stubs/io.pyi
shapely-stubs/lib.pyi
shapely-stubs/linear.pyi
shapely-stubs/measurement.pyi
shapely-stubs/ops.pyi
shapely-stubs/plotting.pyi
shapely-stubs/predicates.pyi
shapely-stubs/prepared.pyi
shapely-stubs/py.typed
shapely-stubs/set_operations.pyi
shapely-stubs/speedups.pyi
shapely-stubs/strtree.pyi
shapely-stubs/testing.pyi
shapely-stubs/validation.pyi
shapely-stubs/wkb.pyi
shapely-stubs/wkt.pyi
shapely-stubs/algorithms/__init__.pyi
shapely-stubs/algorithms/cga.pyi
shapely-stubs/algorithms/polylabel.pyi
shapely-stubs/geometry/__init__.pyi
shapely-stubs/geometry/base.pyi
shapely-stubs/geometry/collection.pyi
shapely-stubs/geometry/geo.pyi
shapely-stubs/geometry/linestring.pyi
shapely-stubs/geometry/multilinestring.pyi
shapely-stubs/geometry/multipoint.pyi
shapely-stubs/geometry/multipolygon.pyi
shapely-stubs/geometry/point.pyi
shapely-stubs/geometry/polygon.pyi
shapely-stubs/vectorized/__init__.pyi
types_shapely-2.1.0.20250915.dist-info/licenses/LICENSE
types_shapely-2.1.0.20250915.dist-info/METADATA
types_shapely-2.1.0.20250915.dist-info/WHEEL
types_shapely-2.1.0.20250915.dist-info/top_level.txt
types_shapely-2.1.0.20250915.dist-info/RECORD
